ovcirrus_api/__init__.py
ovcirrus_api/api_client/__init__.py
ovcirrus_api/api_client/auth.py
ovcirrus_api/api_client/authentication.py
ovcirrus_api/api_client/base.py
ovcirrus_api/api_client/device.py
ovcirrus_api/api_client/organization.py
ovcirrus_api/api_client/ovcapi_client.py
ovcirrus_api/api_client/site.py
ovcirrus_api/api_client/ssid.py
ovcirrus_api/api_client/user.py
ovcirrus_api/api_client/wlananalytics.py
ovcirrus_api/models/__init__.py
ovcirrus_api/models/auth.py
ovcirrus_api/models/authentication.py
ovcirrus_api/models/device.py
ovcirrus_api/models/organization.py
ovcirrus_api/models/site.py
ovcirrus_api/models/ssid.py
ovcirrus_api/models/user.py
ovcirrus_api/models/wlananalytics.py
ovcirrus_api/utilities/__init__.py
ovcirrus_api/utilities/model_validator.py
ovcirrus_api-10.4.3.post13.dist-info/METADATA
ovcirrus_api-10.4.3.post13.dist-info/WHEEL
ovcirrus_api-10.4.3.post13.dist-info/top_level.txt
ovcirrus_api-10.4.3.post13.dist-info/RECORD
